geostatsmodels/__init__.py
geostatsmodels/geoplot.py
geostatsmodels/kriging.py
geostatsmodels/model.py
geostatsmodels/simulation.py
geostatsmodels/utilities.py
geostatsmodels/variograms.py
geostatsmodels/zscoretrans.py
geostatsmodels-0.3.3.dist-info/AUTHORS.md
geostatsmodels-0.3.3.dist-info/METADATA
geostatsmodels-0.3.3.dist-info/WHEEL
geostatsmodels-0.3.3.dist-info/top_level.txt
geostatsmodels-0.3.3.dist-info/RECORD
