Metadata-Version: 2.1
Name: geostatsmodels
Version: 0.3.3
Summary: Kriging and geostatistics tools.
Home-page: https://github.com/cjohnson318/geostatsmodels
Author: Connor Johnson
Author-email: connor.labaume.johnson@gmail.com
License: UNKNOWN
Platform: UNKNOWN
Classifier: Development Status :: 4 - Beta
Classifier: Programming Language :: Python :: 3
Classifier: License :: OSI Approved :: MIT License
